setup.cfg
setup.py
src/hapctl/__init__.py
src/hapctl/haproxy.py
src/hapctl.egg-info/PKG-INFO
src/hapctl.egg-info/SOURCES.txt
src/hapctl.egg-info/dependency_links.txt
src/hapctl.egg-info/entry_points.txt
src/hapctl.egg-info/requires.txt
src/hapctl.egg-info/top_level.txt
src/hapctl/cmd/__init__.py
src/hapctl/cmd/cli.py