Metadata-Version: 1.1
Name: hapctl
Version: 1.0.0
Summary: Communicating with the HAProxy Control Socket
Home-page: https://github.com/serverops/hapctl
Author: Chris Fidao
Author-email: chris@serverops.io
License: MIT
Keywords: haproxy,socket,haproxyctl
Platform: UNKNOWN
Classifier: License :: OSI Approved :: MIT License
Classifier: Operating System :: POSIX
Classifier: Environment :: Console
Classifier: Programming Language :: Python
Classifier: Topic :: Internet :: Proxy Servers
Classifier: Topic :: Software Development :: Libraries :: Python Modules
Classifier: Topic :: System :: Systems Administration
Classifier: Topic :: System :: Networking
